chatbot/__init__.py
chatbot/dingtalk.py
chatbotlib-1.0.7.dist-info/METADATA
chatbotlib-1.0.7.dist-info/WHEEL
chatbotlib-1.0.7.dist-info/top_level.txt
chatbotlib-1.0.7.dist-info/RECORD
