Metadata-Version: 2.1
Name: chatbotlib
Version: 1.0.7
Summary: chatbot
Home-page: https://github.com/Orisdaddy/likeshell
Author: Fizone
Author-email: edeport126@gmail.com
License: Apache License 2.0
Keywords: chat,bot,chatbot,dingding,dingtalk
Platform: any
Classifier: Development Status :: 5 - Production/Stable
Classifier: Intended Audience :: Developers
Classifier: License :: OSI Approved :: Apache Software License
Classifier: Programming Language :: Python
Classifier: Programming Language :: Python :: 3
Classifier: Programming Language :: Python :: 3.6
Classifier: Programming Language :: Python :: 3.7
Classifier: Programming Language :: Python :: 3.8
Classifier: Programming Language :: Python :: 3.9
Requires-Python: >=3.6
Requires-Dist: requests
Requires-Dist: aiohttp
